README.md
setup.py
python_thenewsapi.egg-info/PKG-INFO
python_thenewsapi.egg-info/SOURCES.txt
python_thenewsapi.egg-info/dependency_links.txt
python_thenewsapi.egg-info/requires.txt
python_thenewsapi.egg-info/top_level.txt
thenewsapi/TNAClient.py
thenewsapi/TNAException.py
thenewsapi/__init__.py
thenewsapi/const.py
thenewsapi/utils.py