Metadata-Version: 2.1
Name: python-thenewsapi
Version: 0.1.1
Summary: A python wrapper for thenewsapi.com
Home-page: https://github.com/sandersb725/python-thenewsapi
Author: Brighton Sanders
Author-email: bus120610@gmail.com
License: UNKNOWN
Platform: UNKNOWN
Classifier: Intended Audience :: End Users/Desktop
Classifier: Intended Audience :: Developers
Classifier: Intended Audience :: Information Technology
Classifier: Intended Audience :: System Administrators
Classifier: Operating System :: OS Independent
Classifier: Programming Language :: Python :: 3
